evonik/dummy/__init__.py
evonik/dummy/array.py
evonik/dummy/boolean.py
evonik/dummy/dummy.py
evonik/dummy/enum.py
evonik/dummy/faker.py
evonik/dummy/integer.py
evonik/dummy/json.py
evonik/dummy/number.py
evonik/dummy/object.py
evonik/dummy/string.py
evonik/dummy/test_all.py
evonik/dummy/util.py
evonik_dummy-0.0.13.dist-info/LICENSE
evonik_dummy-0.0.13.dist-info/METADATA
evonik_dummy-0.0.13.dist-info/WHEEL
evonik_dummy-0.0.13.dist-info/top_level.txt
evonik_dummy-0.0.13.dist-info/RECORD
