Metadata-Version: 2.1
Name: evonik-dummy
Version: 0.0.13
Summary: Generate dummy data, e.g., for testing APIs
Home-page: https://evodl.visualstudio.com/evonik-dummy
Author: Benjamin Schiller
Author-email: benjamin.schiller@evonik.com
License: UNKNOWN
Platform: UNKNOWN
Classifier: Programming Language :: Python :: 3
Classifier: License :: OSI Approved :: MIT License
Classifier: Operating System :: OS Independent
Requires-Python: >=3.7
Requires-Dist: exrex (>=0.10.5)
Requires-Dist: faker (>=4.1.1)
Requires-Dist: pytest (>=6.0.1)
